planetra_solver/__init__.py
planetra_solver/config.py
planetra_solver/api/__init__.py
planetra_solver/api/ks_api_chats.py
planetra_solver/api/ks_api_classes.py
planetra_solver/api/ks_api_datasets.py
planetra_solver/api/ks_api_dictionaries.py
planetra_solver/api/ks_api_main.py
planetra_solver/api/ks_api_models.py
planetra_solver/api/ks_api_objects.py
solver/__init__.py
planetra_solver-0.2.3.dist-info/LICENSE
planetra_solver-0.2.3.dist-info/METADATA
planetra_solver-0.2.3.dist-info/WHEEL
planetra_solver-0.2.3.dist-info/top_level.txt
planetra_solver-0.2.3.dist-info/RECORD
